AUTHORS
CHANGELOG
LICENSE
MANIFEST.in
README.rst
setup.py
django_newrelic_extensions.egg-info/PKG-INFO
django_newrelic_extensions.egg-info/SOURCES.txt
django_newrelic_extensions.egg-info/dependency_links.txt
django_newrelic_extensions.egg-info/requires.txt
django_newrelic_extensions.egg-info/top_level.txt
newrelicextensions/__init__.py
newrelicextensions/middleware.py