Metadata-Version: 1.0
Name: django-newrelic-extensions
Version: 0.0.1
Summary: New Relic extensions for Django
Home-page: UNKNOWN
Author: SheepDogInc
Author-email: development@sheepdoginc.ca
License: UNKNOWN
Platform: UNKNOWN
